setup.py
UsageCheck/UsageCheck.py
UsageCheck/__init__.py
UsageCheck.egg-info/PKG-INFO
UsageCheck.egg-info/SOURCES.txt
UsageCheck.egg-info/dependency_links.txt
UsageCheck.egg-info/top_level.txt