Metadata-Version: 2.1
Name: UsageCheck
Version: 0.0.1
Summary: This package is use to check the RAM and CPU Usage of Current Device.
Author: Nidhi Sharma
License: UNKNOWN
Platform: UNKNOWN
